adafruit_macropad.py
adafruit_circuitpython_macropad-2.4.5.dist-info/licenses/LICENSE
adafruit_circuitpython_macropad-2.4.5.dist-info/METADATA
adafruit_circuitpython_macropad-2.4.5.dist-info/WHEEL
adafruit_circuitpython_macropad-2.4.5.dist-info/top_level.txt
adafruit_circuitpython_macropad-2.4.5.dist-info/RECORD
