Metadata-Version: 2.4
Name: adafruit-circuitpython-macropad
Version: 2.4.5
Summary: A helper library for the Adafruit MacroPad RP2040
Author-email: Adafruit Industries <circuitpython@adafruit.com>
License: MIT
Project-URL: Homepage, https://github.com/adafruit/Adafruit_CircuitPython_MacroPad
Keywords: adafruit,macropad,rp2040,mechanical,keyboard,breakout,hardwaremicropython,circuitpython
Classifier: Intended Audience :: Developers
Classifier: Topic :: Software Development :: Libraries
Classifier: Topic :: Software Development :: Embedded Systems
Classifier: Topic :: System :: Hardware
Classifier: License :: OSI Approved :: MIT License
Classifier: Programming Language :: Python :: 3
License-File: LICENSE
Requires-Dist: Adafruit-Blinka
Requires-Dist: adafruit-circuitpython-hid
Requires-Dist: adafruit-circuitpython-midi
Requires-Dist: adafruit-circuitpython-display-text
Requires-Dist: adafruit-circuitpython-debouncer
Requires-Dist: adafruit-circuitpython-simple-text-display
Requires-Dist: adafruit-circuitpython-neopixel
Provides-Extra: optional
Dynamic: license-file
